hatch_jupyter_builder/__init__.py
hatch_jupyter_builder/__main__.py
hatch_jupyter_builder/cli.py
hatch_jupyter_builder/hooks.py
hatch_jupyter_builder/plugin.py
hatch_jupyter_builder/py.typed
hatch_jupyter_builder/utils.py
hatch_jupyter_builder/compare_migrated/__init__.py
hatch_jupyter_builder/compare_migrated/__main__.py
hatch_jupyter_builder/compare_migrated/cli.py
hatch_jupyter_builder/migrate/__init__.py
hatch_jupyter_builder/migrate/__main__.py
hatch_jupyter_builder/migrate/_migrate.py
hatch_jupyter_builder/migrate/cli.py
hatch_jupyter_builder/migrate/jupyter_packaging.py
hatch_jupyter_builder-0.9.0.dist-info/METADATA
hatch_jupyter_builder-0.9.0.dist-info/WHEEL
hatch_jupyter_builder-0.9.0.dist-info/entry_points.txt
hatch_jupyter_builder-0.9.0.dist-info/licenses/LICENSE.txt
hatch_jupyter_builder-0.9.0.dist-info/RECORD
