Metadata-Version: 2.1
Name: hatch-jupyter-builder
Version: 0.9.0
Summary: A hatch plugin to help build Jupyter packages
Project-URL: Documentation, https://github.com/jupyterlab/hatch-jupyter-builder#readme
Project-URL: Issues, https://github.com/jupyterlab/hatch-jupyter-builder/issues
Project-URL: Source, https://github.com/jupyterlab/hatch-jupyter-builder
Author-email: Jupyter Development Team <jupyter@googlegroups.com>
License: Copyright (c) 2022 Project Jupyter Contributors
License-File: LICENSE.txt
Keywords: hatch,jupyter,jupyterlab
Classifier: Development Status :: 4 - Beta
Classifier: License :: OSI Approved :: BSD License
Classifier: Programming Language :: Python
Classifier: Programming Language :: Python :: 3 :: Only
Classifier: Programming Language :: Python :: Implementation :: CPython
Classifier: Programming Language :: Python :: Implementation :: PyPy
Requires-Python: >=3.8
Requires-Dist: hatchling>=1.17
Provides-Extra: docs
Requires-Dist: hatch-jupyter-builder; extra == 'docs'
Requires-Dist: myst-parser; extra == 'docs'
Requires-Dist: pydata-sphinx-theme; extra == 'docs'
Requires-Dist: sphinx-autodoc-typehints; extra == 'docs'
Requires-Dist: sphinxcontrib-spelling; extra == 'docs'
Provides-Extra: test
Requires-Dist: hatch; extra == 'test'
Requires-Dist: pytest; extra == 'test'
Requires-Dist: pytest-cov; extra == 'test'
Requires-Dist: pytest-mock; extra == 'test'
Requires-Dist: tomli; extra == 'test'
Requires-Dist: twine; extra == 'test'
